speaker_diarization/__init__.py
speaker_diarization/cli.py
speaker_diarization/speaker_diarization.py
speaker_diarization-0.0.6.dist-info/LICENSE
speaker_diarization-0.0.6.dist-info/METADATA
speaker_diarization-0.0.6.dist-info/WHEEL
speaker_diarization-0.0.6.dist-info/entry_points.txt
speaker_diarization-0.0.6.dist-info/top_level.txt
speaker_diarization-0.0.6.dist-info/RECORD
